{
  "schemaVersion": 1,
  "id": "sweet_potato",
  "version": "${version}",

  "name": "Sweet Potato Mod",
  "description": "Try new kinds of food, crops & magic in Sweet Potato Mod!",
  "authors": [
    "Pigeonia Featurehouse"
  ],
  "contributors": [
    "teddyxlandlee",
    "Rayawa",
    "Peterice"
  ],
  "contact": {
    "homepage": "https://www.curseforge.com/minecraft/mc-mods/sweet-potato",
    "sources": "https://github.com/Featurehouse/sweet_potato-source",
    "issues": "https://github.com/Featurehouse/sweet_potato-issueTracker/issues"
  },

  "license": "Apache-2.0",
  "icon": "assets/sweet_potato/icon.png",

  "environment": "*",
  "entrypoints": {
    "main": [
      "org.featurehouse.mcmod.spm.SPMMain"
    ],
    "client": [
      "org.featurehouse.mcmod.spm.client.SPMClient"
    ],
    "server": [
      "org.featurehouse.mcmod.spm.linkage.SPMLinkageServer::load"
    ]
  },
  "mixins": [
    "sweet_potato.mixins.json"
  ],

  "depends": {
    "fabricloader": ">=0.13.0",
    "fabric": ">=0.47.0",
    "minecraft": ">=1.18.2-alpha.22.6.a",
    "java": ">=17"
  },
  "suggests": {
    "shurlin": "*"
  },
  "custom": {
    "Pigeonia Linkage Standard": {
      "url": "https://featurehouse.github.io/pigeonia-linkage-standard/v1.0.1/STANDARD.txt",
      "version": "v1.0.1",
      "strict": true
    }
  }
}
